aiograph/__init__.py
aiograph/api.py
aiograph/types/__init__.py
aiograph/types/account.py
aiograph/types/base.py
aiograph/types/converters.py
aiograph/types/node.py
aiograph/types/page.py
aiograph/types/page_list.py
aiograph/types/page_views.py
aiograph/utils/__init__.py
aiograph/utils/exceptions.py
aiograph/utils/html.py
aiograph-0.2.dist-info/LICENSE
aiograph-0.2.dist-info/METADATA
aiograph-0.2.dist-info/WHEEL
aiograph-0.2.dist-info/top_level.txt
aiograph-0.2.dist-info/RECORD
