Metadata-Version: 2.1
Name: aiograph
Version: 0.2
Summary: asynchronous Python Telegra.ph API wrapper
Home-page: https://github.com/aiogram/aiograph
Author: Alex Root Junior
Author-email: aiogram@illemius.xyz
Maintainer: Alex Root Junior <jroot.junior@gmail.com>
Maintainer-email: aiogram@illemius.xyz
License: MIT
Platform: UNKNOWN
Classifier: Development Status :: 5 - Production/Stable
Classifier: Environment :: Console
Classifier: Framework :: AsyncIO
Classifier: Intended Audience :: Developers
Classifier: Intended Audience :: System Administrators
Classifier: License :: OSI Approved :: MIT License
Classifier: Programming Language :: Python :: 3.7
Classifier: Topic :: Software Development :: Libraries :: Application Frameworks
Requires-Dist: aiohttp (>=3.4.4)
Requires-Dist: certifi (>=2018.11.29)
Requires-Dist: attrs (>=19.1.0)
Provides-Extra: dev
Requires-Dist: aiohttp (>=3.4.4) ; extra == 'dev'
Requires-Dist: certifi (>=2018.11.29) ; extra == 'dev'
Requires-Dist: attrs (>=19.1.0) ; extra == 'dev'
Requires-Dist: aiohttp-socks (>=0.2.2) ; extra == 'dev'
Requires-Dist: pytest (>=3.5.1) ; extra == 'dev'
Requires-Dist: pytest-asyncio (>=0.8.0) ; extra == 'dev'
Requires-Dist: pytest-cov (>=2.5.1) ; extra == 'dev'
Requires-Dist: wheel (>=0.31.0) ; extra == 'dev'
Requires-Dist: codecov (>=2.0.15) ; extra == 'dev'
